hotbuckets.py
hotbuckets-0.1.1.dist-info/entry_points.txt
hotbuckets-0.1.1.dist-info/WHEEL
hotbuckets-0.1.1.dist-info/METADATA
hotbuckets-0.1.1.dist-info/RECORD
