Metadata-Version: 2.1
Name: hotbuckets
Version: 0.1.1
Summary: Easily configure your network behavior on Linux (generates tc rules from a config)
License: MIT
Author: fdev31
Author-email: fdev31@gmail.com
Requires-Python: >=3.6.1
Classifier: License :: OSI Approved :: MIT License
Classifier: Programming Language :: Python :: 3
Classifier: Programming Language :: Python :: 3.7
Classifier: Programming Language :: Python :: 3.8
Classifier: Programming Language :: Python :: 3.9
Classifier: Programming Language :: Python :: 3.10
Provides-Extra: viz
Requires-Dist: tomli (>=1.0.1)
